simba/__init__.py
simba/config.py
simba/core.py
simba/errors.py
simba/graph.py
simba/utils.py
quantum_simba-0.9.6.dev0.dist-info/LICENSE
quantum_simba-0.9.6.dev0.dist-info/METADATA
quantum_simba-0.9.6.dev0.dist-info/WHEEL
quantum_simba-0.9.6.dev0.dist-info/top_level.txt
quantum_simba-0.9.6.dev0.dist-info/RECORD
