Metadata-Version: 2.1
Name: quantum-simba
Version: 0.9.6.dev0
Summary: Systematic realisation of quantum systems directly from transfer function.
Home-page: https://github.com/joebentley/simba
Author: Joe Bentley
Author-email: joebentley10@gmail.com
License: MIT
Platform: UNKNOWN
Classifier: Programming Language :: Python :: 3
Classifier: License :: OSI Approved :: MIT License
Classifier: Operating System :: OS Independent
Requires-Python: >=3.6
Requires-Dist: numpy
Requires-Dist: scipy
Requires-Dist: sympy (>=1.5.1)
Requires-Dist: pytest
